evo/compute/__init__.py
evo/compute/client.py
evo/compute/data.py
evo/compute/exceptions.py
evo/compute/endpoints/__init__.py
evo/compute/endpoints/models.py
evo/compute/endpoints/api/__init__.py
evo/compute/endpoints/api/jobs_api.py
evo/compute/endpoints/api/tasks_api.py
evo_compute-0.0.1rc3.dist-info/METADATA
evo_compute-0.0.1rc3.dist-info/WHEEL
evo_compute-0.0.1rc3.dist-info/licenses/LICENSE.md
evo_compute-0.0.1rc3.dist-info/RECORD
