Metadata-Version: 2.4
Name: evo-compute
Version: 0.0.1rc3
Project-URL: Source, https://github.com/SeequentEvo/evo-python-sdk
Project-URL: Tracker, https://github.com/SeequentEvo/evo-python-sdk/issues
Project-URL: Homepage, https://www.seequent.com/
Project-URL: Documentation, https://developer.seequent.com/
Author-email: Seequent <support@seequent.com>
License-File: LICENSE.md
Requires-Python: >=3.10
Requires-Dist: evo-sdk-common
Requires-Dist: pydantic>=2
Provides-Extra: aiohttp
Requires-Dist: evo-sdk-common[aiohttp]; extra == 'aiohttp'
Provides-Extra: notebooks
Requires-Dist: evo-sdk-common[notebooks]; extra == 'notebooks'
